droneblocks/DroneBlocksContextManager.py
droneblocks/DroneBlocksTello.py
droneblocks/__init__.py
droneblocks/tello_keyboard_mapper.py
droneblocks/tello_script_runner.py
droneblocks/tello_web.py
droneblocks/template_user_script.py
droneblocks/template_user_script_keypad.py
droneblocks/tt_matrix_generator.py
droneblocks/uielements.py
droneblocks/data/8x8-matrix-hotspots2.csv
droneblocks/data/joystick_hotspots3.csv
droneblocks/data/placeholder.txt
droneblocks/media/8x8matrix_expansion.png
droneblocks/media/DB_app_darkblue_1024.jpg
droneblocks/media/DB_app_white_1024.jpg
droneblocks/media/DB_logo_400px.jpg
droneblocks/media/DB_logo_400px_100px.jpg
droneblocks/media/droneblocks_logo.png
droneblocks/media/tello-controller-left.jpeg
droneblocks/media/tello-controller-right.jpeg
droneblocks/media/tello-controller.png
droneblocks/media/tello_drone_image.png
droneblocks/media/tello_drone_image2.png
droneblocks/web/index.html
droneblocks/web/landing.html
droneblocks/web/static/css/neumorphism.css
droneblocks/web/static/css/neumorphism.css.map
droneblocks/web/static/images/droneblocks_logo.png
droneblocks/web/static/images/rm_tt_transparent.png
droneblocks/web/static/images/tello-controller.png
droneblocks/web/static/images/tello_drone_image2.png
droneblocks/web/static/js/axios.min.js
droneblocks/web/static/js/neumorphism.js
droneblocks/web/static/js/vue.min.js
droneblocksutils/__init__.py
droneblocksutils/aruco_utils.py
droneblocksutils/exceptions.py
droneblocksutils/image_effects.py
droneblocks_python_utils-0.2.2.dist-info/LICENSE
droneblocks_python_utils-0.2.2.dist-info/METADATA
droneblocks_python_utils-0.2.2.dist-info/WHEEL
droneblocks_python_utils-0.2.2.dist-info/entry_points.txt
droneblocks_python_utils-0.2.2.dist-info/top_level.txt
droneblocks_python_utils-0.2.2.dist-info/RECORD
