Metadata-Version: 2.1
Name: droneblocks-python-utils
Version: 0.2.2
Summary: DroneBlocks Python Utilities
Home-page: https://github.com/dbaldwin/DroneBlocks-Python-Utils
Author: Patrick Ryan, Dennis Baldwin
Author-email: db@droneblocks.io
License: MIT
License-File: LICENSE
Requires-Dist: opencv-python (==4.5.5.62)
Requires-Dist: opencv-contrib-python (==4.5.5.62)
Requires-Dist: imutils (==0.5.4)
Requires-Dist: djitellopy (==2.4)
Requires-Dist: bottle (==0.12.19)
